activity_plots/__init__.py
activity_plots/data.py
activity_plots/plots.py
activity_plots-0.0.1.dist-info/METADATA
activity_plots-0.0.1.dist-info/WHEEL
activity_plots-0.0.1.dist-info/licenses/LICENSE
activity_plots-0.0.1.dist-info/RECORD
