Metadata-Version: 2.4
Name: activity-plots
Version: 0.0.1
Summary: Activity/event timeline visualization for action localization (or detection) labels and predictions.
Project-URL: Repository, https://github.com/mpeven/activity-plots.git
Author-email: Mike Peven <mpeven@gmail.com>
License-Expression: MIT
License-File: LICENSE
Keywords: activity,plotting,timeline
Classifier: Development Status :: 4 - Beta
Classifier: Programming Language :: Python
Requires-Python: >=3.9
Requires-Dist: colormaps
Requires-Dist: matplotlib>=3.10.0
Requires-Dist: numpy>=2.1.0
Requires-Dist: packaging>=21.0
Requires-Dist: pandas>=2.2.0
Provides-Extra: examples
Requires-Dist: seaborn; extra == 'examples'
Provides-Extra: test
Requires-Dist: pytest; extra == 'test'
